b4sh/__init__.py
b4sh/__main__.py
b4sh/module.py
b4sh/settings.py
b4sh/utils/__init__.py
b4sh/utils/create.py
b4sh/utils/find.py
b4sh/utils/get.py
b4sh/utils/helpers.py
b4sh/utils/list.py
b4sh-0.1.0.2.data/scripts/b
b4sh-0.1.0.2.data/scripts/b4sh
b4sh-0.1.0.2.dist-info/LICENSE.txt
b4sh-0.1.0.2.dist-info/METADATA
b4sh-0.1.0.2.dist-info/WHEEL
b4sh-0.1.0.2.dist-info/top_level.txt
b4sh-0.1.0.2.dist-info/RECORD
