Metadata-Version: 2.1
Name: b4sh
Version: 0.1.0.2
Summary: Create, use and share bashs commands
Home-page: https://github.com/sanix-darker/b4sh
Author: Sanix-darker
Author-email: s4nixd@gmail.com
License: UNKNOWN
Platform: UNKNOWN
Classifier: Programming Language :: Python :: 3
Classifier: License :: OSI Approved :: MIT License
Classifier: Operating System :: OS Independent
Requires-Python: >=3.6
